{"engine":"ember-template-lint","filePath":"app/templates/records/show.hbs","ruleId":"no-action","range":{"start":{"line":31,"column":29},"end":{"line":31,"column":29}},"source":"c4d1ca4d74238802acf97f9d748a1729161f3ebd","originalLintResult":{"rule":"no-action","severity":2,"filePath":"app/templates/records/show.hbs","line":31,"column":29,"endLine":31,"endColumn":57,"source":"{{action 'saveRecordEdits'}}","message":"Do not use `action` as <button {{action ...}} />. Instead, use the `on` modifier and `fn` helper."},"fileFormat":2,"createdDate":1651276800000,"warnDate":1653868800000,"errorDate":1656460800000}
